.DS_Store
jasonTest/test1.py
jasonTest/test2.py
jasonTest2024/test1.py
jasonTest2024/test2.py
jasonTest2024-0.0.0.2.dist-info/METADATA
jasonTest2024-0.0.0.2.dist-info/WHEEL
jasonTest2024-0.0.0.2.dist-info/top_level.txt
jasonTest2024-0.0.0.2.dist-info/RECORD
