Metadata-Version: 2.1
Name: jasonTest2024
Version: 0.0.0.2
Summary: My First Test
Home-page: https://www.naver.com
Author: Ju Dang
Author-email: david766589@gmail.com
License: MIT
Requires-Python: >=3.6
